{
    "aboutme": "",
    "edu": [{
        "time": "",
        "content": ""
    }],
    "work": [
        {
            "time": "",
            "company": "",
            "position": ""
        },
        {
            "time": "",
            "company": "",
            "position": ""
        },
        {
            "time": "",
            "company": "",
            "position": ""
        }
    ],
    "projects": [
        {
            "name": "",
            "time": "",
            "link": "",
            "code": "",
            "content": "",
            "tags": [""]
        },
        {
            "name": "",
            "time": "",
            "link": "",
            "code": "",
            "content": "",
            "tags": [""]
        },
        {
            "name": "",
            "time": "",
            "link": "",
            "code": "",
            "content": "",
            "tags": [""]
        }
    ],
    "github": [
        {
            "name": "",
            "time": "",
            "link": "",
            "code": "",
            "content": "",
            "tags": [""]
        },
        {
            "name": "",
            "time": "",
            "link": "",
            "code": "",
            "content": "",
            "tags": [""]
        },
        {
            "name": "",
            "time": "",
            "link": "",
            "code": "",
            "content": "",
            "tags": [""]
        }
    ],
    "connectme": [
        {
            "icon": "",
            "link": "",
            "content": ""
        },
        {
            "icon": "",
            "link": "",
            "content": ""
        },
        {
            "icon": "",
            "link": "",
            "content": ""
        }
    ]
}